{
  "signal": "neutral",
  "label": "⚖️  중립",
  "total_score": -0.54,
  "confidence": 14.8,
  "xgboost_prob": 0.22,
  "xgboost_adj": -1.5,
  "axis_scores": {
    "technical": -0.15,
    "fundamental": -3.75,
    "financial": 7.9,
    "macro": -1.3,
    "sentiment": 0.0
  },
  "axis_weights": {
    "technical": 0.35,
    "fundamental": 0.1,
    "financial": 0.2,
    "macro": 0.15,
    "sentiment": 0.2
  },
  "contributions": {
    "technical": -0.052,
    "fundamental": -0.375,
    "financial": 1.58,
    "macro": -0.195,
    "sentiment": 0.0
  },
  "analysis_date": "2026-03-31 14:13",
  "stock": "삼성전자",
  "insider_trades": [
    {
      "date": "2026-03-31",
      "name": "송기재",
      "type": "buy",
      "shares": 397,
      "value": 69991100.0
    },
    {
      "date": "2026-03-30",
      "name": "조성희",
      "type": "buy",
      "shares": 2910,
      "value": 513033000.0
    },
    {
      "date": "2026-03-30",
      "name": "김보현",
      "type": "buy",
      "shares": 164,
      "value": 28913200.0
    },
    {
      "date": "2026-03-20",
      "name": "이승민",
      "type": "buy",
      "shares": 166,
      "value": 29265800.0
    },
    {
      "date": "2026-03-17",
      "name": "조영준",
      "type": "buy",
      "shares": 2885,
      "value": 508625500.0
    },
    {
      "date": "2026-03-13",
      "name": "송재혁",
      "type": "buy",
      "shares": 20,
      "value": 3526000.0
    },
    {
      "date": "2026-03-13",
      "name": "오문욱",
      "type": "buy",
      "shares": 500,
      "value": 88150000.0
    },
    {
      "date": "2026-03-10",
      "name": "박기루",
      "type": "buy",
      "shares": 15,
      "value": 2644500.0
    },
    {
      "date": "2026-03-06",
      "name": "장우영",
      "type": "sell",
      "shares": 50,
      "value": 8815000.0
    },
    {
      "date": "2026-03-06",
      "name": "강상균",
      "type": "buy",
      "shares": 114,
      "value": 20098200.0
    },
    {
      "date": "2026-03-05",
      "name": "홍창표",
      "type": "buy",
      "shares": 100,
      "value": 17630000.0
    },
    {
      "date": "2026-03-03",
      "name": "정성원",
      "type": "sell",
      "shares": 275,
      "value": 48482500.0
    },
    {
      "date": "2026-03-03",
      "name": "Lee Dae Jun",
      "type": "buy",
      "shares": 62,
      "value": 10930600.0
    },
    {
      "date": "2026-02-27",
      "name": "최윤성",
      "type": "buy",
      "shares": 42,
      "value": 7404600.0
    },
    {
      "date": "2026-02-27",
      "name": "박병수",
      "type": "sell",
      "shares": 1000,
      "value": 176300000.0
    },
    {
      "date": "2026-02-23",
      "name": "이강승",
      "type": "sell",
      "shares": 400,
      "value": 70520000.0
    },
    {
      "date": "2026-02-20",
      "name": "소피아황",
      "type": "sell",
      "shares": 420,
      "value": 74046000.0
    },
    {
      "date": "2026-02-20",
      "name": "박상욱",
      "type": "buy",
      "shares": 286,
      "value": 50421800.0
    },
    {
      "date": "2026-02-12",
      "name": "포르치니마우로",
      "type": "sell",
      "shares": 13293,
      "value": 2343555900.0
    },
    {
      "date": "2026-02-11",
      "name": "이승연",
      "type": "buy",
      "shares": 111,
      "value": 19569300.0
    }
  ]
}